setup.cfg
setup.py
encrypted_storage/__init__.py
encrypted_storage.egg-info/PKG-INFO
encrypted_storage.egg-info/SOURCES.txt
encrypted_storage.egg-info/dependency_links.txt
encrypted_storage.egg-info/pbr.json
encrypted_storage.egg-info/requires.txt
encrypted_storage.egg-info/top_level.txt