Metadata-Version: 1.1
Name: encrypted-storage
Version: 1.0.1
Summary: Easy, cryptographically secure storage on numerous database backends.
Home-page: https://github.com/Kazanz/encrypted_storage
Author: Zach Kazanski
Author-email: kazanski.zachary@gmail.com
License: UNKNOWN
Download-URL: https://github.com/kazanz/encrypted_storage/tarball/1.0.0
Keywords: cryptography,encryption
Platform: UNKNOWN
Classifier: Programming Language :: Python
Classifier: Development Status :: 5 - Production/Stable
Classifier: Intended Audience :: Developers
Classifier: Operating System :: OS Independent
Classifier: License :: OSI Approved :: MIT License
Classifier: Programming Language :: Python :: 2.7
Classifier: Topic :: Security :: Cryptography
